x_make_pip_updates_x/__init__.py
x_make_pip_updates_x/x_cls_make_pip_updates_x.py
x_make_pip_updates_x-12.0.0.dist-info/METADATA
x_make_pip_updates_x-12.0.0.dist-info/WHEEL
x_make_pip_updates_x-12.0.0.dist-info/top_level.txt
x_make_pip_updates_x-12.0.0.dist-info/RECORD
